byted_overpass_life_goods_product_recognition/__init__.py
byted_overpass_life_goods_product_recognition-0.0.1.dist-info/METADATA
byted_overpass_life_goods_product_recognition-0.0.1.dist-info/WHEEL
byted_overpass_life_goods_product_recognition-0.0.1.dist-info/top_level.txt
byted_overpass_life_goods_product_recognition-0.0.1.dist-info/RECORD
